smap_effect_prediction/__init__.py
smap_effect_prediction/__main__.py
smap_effect_prediction/__version__.py
smap_effect_prediction/editor.py
smap_effect_prediction/logging_configuration.py
smap_effect_prediction/models.py
smap_effect_prediction/plotting.py
smap_effect_prediction/utils.py
smap_effect_prediction/modifications/__init__.py
smap_effect_prediction/modifications/aggregate.py
smap_effect_prediction/modifications/annotate.py
smap_effect_prediction/modifications/collapse.py
smap_effect_prediction/modifications/discretize.py
smap_effect_prediction/modifications/modification.py
smap_effect_prediction-0.1.2.dist-info/LICENSE
smap_effect_prediction-0.1.2.dist-info/METADATA
smap_effect_prediction-0.1.2.dist-info/WHEEL
smap_effect_prediction-0.1.2.dist-info/entry_points.txt
smap_effect_prediction-0.1.2.dist-info/top_level.txt
smap_effect_prediction-0.1.2.dist-info/RECORD
