Metadata-Version: 2.1
Name: smap-effect-prediction
Version: 0.1.2
Home-page: https://ngs-smap.readthedocs.io/en/latest/
Author-email: dries.schaumont@ilvo.vlaanderen.be
License: GNU General Public License v3 (GPLv3)
Classifier: Programming Language :: Python :: 3
Classifier: License :: OSI Approved :: GNU Affero General Public License v3
Requires-Python: >=3.8
License-File: LICENSE
Requires-Dist: ngs-smap (<=4.7,>=4.5)
Requires-Dist: pandas (~=1.4.2)
Requires-Dist: pybedtools (~=0.9.0)
Requires-Dist: biopython (~=1.78)
Requires-Dist: gffpandas (~=1.2.0)
Requires-Dist: plotly (~=5.3.1)
Requires-Dist: openpyxl (~=3.0.9)
Requires-Dist: colorlog (~=6.6.0)
Requires-Dist: typing-extensions (~=4.0.0)
Provides-Extra: docs
Requires-Dist: sphinx (~=4.4.0) ; extra == 'docs'
Requires-Dist: sphinx-rtd-theme (~=1.0.0) ; extra == 'docs'
Requires-Dist: sphinx-argparse (~=0.3.1) ; extra == 'docs'
Requires-Dist: sphinx-tabs (~=3.3.1) ; extra == 'docs'
Requires-Dist: sphinx-subprojecttoctree (~=0.3.1) ; extra == 'docs'
